{
    "configurations": {
        "default_readonly": {
            "url": "http://132.249.245.245:24342",
            "channel": "public",
            "password": "public"
        },
        "default_readwrite": {
            "url": "http://132.249.245.245:24342",
            "channel": "neuro",
            "password": {"env": "KACHERY_DEFAULT_PASSWORD"}
        },
        "labbox_ephys_readonly": {
            "url": "http://52.9.11.30:8080",
            "channel": "labbox_ephys_readwrite",
            "password": {"env": "LABBOX_EPHYS_KACHERY_READWRITE_PASSWORD"}
        },
        "labbox_ephys_readwrite": {
            "url": "http://52.9.11.30:8080",
            "channel": "labbox_ephys_readwrite",
            "password": {"env": "LABBOX_EPHYS_KACHERY_READWRITE_PASSWORD"}
        }
    }
}
